uvicorn_httparse/__init__.py
uvicorn_httparse/protocol.py
uvicorn_httparse/py.typed
uvicorn_httparse-0.1.0.dist-info/METADATA
uvicorn_httparse-0.1.0.dist-info/WHEEL
uvicorn_httparse-0.1.0.dist-info/RECORD
