Metadata-Version: 2.1
Name: uvicorn-httparse
Version: 0.1.0
Summary: Uvicorn HTTP implementation using httparse! 🏃
Author-email: Marcelo Trylesinski <marcelotryle@gmail.com>
License: MIT
Requires-Python: >=3.7
Requires-Dist: httparse>=0.2.1
Requires-Dist: uvicorn>=0.19.0
